MANIFEST.in
README.md
setup.py
satnet/__init__.py
satnet/models.py
satnet.egg-info/PKG-INFO
satnet.egg-info/SOURCES.txt
satnet.egg-info/dependency_links.txt
satnet.egg-info/not-zip-safe
satnet.egg-info/requires.txt
satnet.egg-info/top_level.txt
src/satnet.cpp
src/satnet.h
src/satnet_cpu.cpp
src/satnet_cuda.cu