Metadata-Version: 2.1
Name: satnet
Version: 0.1.2
Summary: Bridging deep learning and logical reasoning using a differentiable satisfiability solver
Home-page: https://github.com/locuslab/SATNet
Author: Po-Wei Wang
Author-email: poweiw@cs.cmu.edu
License: UNKNOWN
Platform: UNKNOWN
Classifier: License :: OSI Approved :: MIT License
